{
    "plugin": {
        "description": "Initializes a new jinitializer plugin project.",
        "commands": {
            "plugins": [ 
                "create-plugin"
            ]
        }
    },
    "laravel-local": { 
        "description": "Initializes a new local laravel project.",
        "onAbort": {
            "shell": [
                "rm -r [PROJECT_DIRECTORY]"
            ]
        },
        "commands": {
            "mysql": [
                "create-database",
                "create-user"
            ],
            "composer": [
                "create-project laravel/laravel"
            ],
            ".env": [
                "set-value DB_CONNECTION mysql",
                "set-value DB_DATABASE",
                "set-value DB_USERNAME",
                "set-value DB_PASSWORD"
            ],
            "shell": [
                "tags"
            ],
            "git": [
                "init",
                "create-upstream-bitbucket",
                "ignore --tags"
            ],
            "apache2": [
                "create-site-local",
                "reload",
                "setup host"
            ],
            "shell": [
                "composer install",
                "npm install",
                "chgrp -R www-data {APP_PATH}/{APP_NAME}"
            ]
        }
    },
    "php-package": {
        "description": "Create a new generic php package.",
        "commands": [ 
            "project:create",
            "project:folder src",
            "project:folder tests",
            "project:folder tests/Unit",
            "project:folder tests/Feature",
            "project:folder tests/Traits",
            "project:folder tests/output",
            "project:copy phpunit.xml",
            "project:copy-stub composer.stub",
            "git:init",
            "git:create-upstream-github",
            "git:ignore tags",
            "git:ignore vendor",
            "git:ignore tests/output",
            "shell:\"ctags -R --fields=+laimS --languages=php --exclude=.git\""
        ]
    }
}
